LICENSE
MANIFEST.in
README.md
install_script.py
setup.py
kdFileFinder/__init__.py
kdFileFinder/bookmark.py
kdFileFinder/center.py
kdFileFinder/customer_script.py
kdFileFinder/customer_script.ui
kdFileFinder/customer_script_ui.py
kdFileFinder/exception_handler.py
kdFileFinder/fileutil.py
kdFileFinder/kdFileFinder.py
kdFileFinder/kdFileFinder.ui
kdFileFinder/kdFileFinder_ui.py
kdFileFinder/kdconfig.py
kdFileFinder/menu.py
kdFileFinder/scriptManager.py
kdFileFinder/scriptManager.ui
kdFileFinder/script_manager_ui.py
kdFileFinder/sidebar.py
kdFileFinder/toolbar.py
kdFileFinder.egg-info/PKG-INFO
kdFileFinder.egg-info/SOURCES.txt
kdFileFinder.egg-info/dependency_links.txt
kdFileFinder.egg-info/entry_points.txt
kdFileFinder.egg-info/not-zip-safe
kdFileFinder.egg-info/requires.txt
kdFileFinder.egg-info/top_level.txt
kdFileFinder/data/__init__.py
kdFileFinder/data/abort.png
kdFileFinder/data/application-x-executable.png
kdFileFinder/data/applications-system.png
kdFileFinder/data/bookmark-book.png
kdFileFinder/data/bookmark-item.png
kdFileFinder/data/clock.png
kdFileFinder/data/computer.ico
kdFileFinder/data/config.ini
kdFileFinder/data/device.png
kdFileFinder/data/document-new.png
kdFileFinder/data/document-open.png
kdFileFinder/data/document-properties.png
kdFileFinder/data/drive-harddisk-usb.png
kdFileFinder/data/edit-copy.png
kdFileFinder/data/edit-cut.png
kdFileFinder/data/edit-delete.png
kdFileFinder/data/edit-find.png
kdFileFinder/data/edit-paste.png
kdFileFinder/data/edit-redo.png
kdFileFinder/data/edit-rename.png
kdFileFinder/data/edit-select-all.png
kdFileFinder/data/edit-undo.png
kdFileFinder/data/error.png
kdFileFinder/data/eye.png
kdFileFinder/data/folder-new.png
kdFileFinder/data/folder.png
kdFileFinder/data/go-down.png
kdFileFinder/data/go-home.png
kdFileFinder/data/go-next.png
kdFileFinder/data/go-previous.png
kdFileFinder/data/go-up.png
kdFileFinder/data/gtk-edit.png
kdFileFinder/data/history-folder.png
kdFileFinder/data/history-item.png
kdFileFinder/data/history-time.png
kdFileFinder/data/kdFileFinder.png
kdFileFinder/data/list-add.png
kdFileFinder/data/list-remove.png
kdFileFinder/data/menu.png
kdFileFinder/data/mouse.png
kdFileFinder/data/ok.png
kdFileFinder/data/point-up.png
